ad9xdds/__init__.py
ad9xdds/ad9854dev.py
ad9xdds/ad9912dev.py
ad9xdds/ad9915dev_bbb.py
ad9xdds/ad9915dev_umr232hm.py
ad9xdds/dds_core.py
ad9xdds/dds_emul.py
ad9xdds/qad9912dev.py
ad9xdds/sad9912dev.py
ad9xdds/sad9915dev_umr232hm.py
ad9xdds/version.py
ad9xdds-0.5.11.data/scripts/ad9915-cli
ad9xdds-0.5.11.dist-info/licenses/LICENSE.txt
ad9xdds-0.5.11.dist-info/METADATA
ad9xdds-0.5.11.dist-info/WHEEL
ad9xdds-0.5.11.dist-info/top_level.txt
ad9xdds-0.5.11.dist-info/RECORD
