Metadata-Version: 2.4
Name: ad9xdds
Version: 0.5.11
Summary: Ad9xDds is library dedicated to handle AD9854, AD9912 and AD9915 DDS development board.
Home-page: https://gitlab.com/bendub/ad9xdds
Author: Benoit Dubois
Author-email: benoit.dubois@femto-enginneering.fr
License: LGPL-3.0-or-later
Classifier: Development Status :: 4 - Beta
Classifier: Intended Audience :: Developers
Classifier: Natural Language :: English
Classifier: Operating System :: POSIX :: Linux
Classifier: Programming Language :: Python
Classifier: Topic :: Scientific/Engineering
License-File: LICENSE.txt
Requires-Dist: iopy>=0.2.0
Requires-Dist: pyftdi
Provides-Extra: pure-python-signalslot-facilities
Requires-Dist: signalslot; extra == "pure-python-signalslot-facilities"
Provides-Extra: pyqt-signalslot-facilities
Requires-Dist: PyQt5; extra == "pyqt-signalslot-facilities"
Provides-Extra: ad9854-support
Requires-Dist: pyparallel; extra == "ad9854-support"
Dynamic: author
Dynamic: author-email
Dynamic: classifier
Dynamic: home-page
Dynamic: license
Dynamic: license-file
Dynamic: provides-extra
Dynamic: requires-dist
Dynamic: summary
